parallel_web_tools/__init__.py
parallel_web_tools/cli/__init__.py
parallel_web_tools/cli/commands.py
parallel_web_tools/cli/planner.py
parallel_web_tools/cli/updater.py
parallel_web_tools/core/__init__.py
parallel_web_tools/core/auth.py
parallel_web_tools/core/batch.py
parallel_web_tools/core/research.py
parallel_web_tools/core/result.py
parallel_web_tools/core/runner.py
parallel_web_tools/core/schema.py
parallel_web_tools/core/user_agent.py
parallel_web_tools/integrations/__init__.py
parallel_web_tools/integrations/utils.py
parallel_web_tools/integrations/bigquery/__init__.py
parallel_web_tools/integrations/bigquery/deploy.py
parallel_web_tools/integrations/bigquery/cloud_function/main.py
parallel_web_tools/integrations/bigquery/cloud_function/requirements.txt
parallel_web_tools/integrations/bigquery/sql/create_functions.sql
parallel_web_tools/integrations/duckdb/__init__.py
parallel_web_tools/integrations/duckdb/batch.py
parallel_web_tools/integrations/duckdb/udf.py
parallel_web_tools/integrations/polars/__init__.py
parallel_web_tools/integrations/polars/enrich.py
parallel_web_tools/integrations/snowflake/__init__.py
parallel_web_tools/integrations/snowflake/deploy.py
parallel_web_tools/integrations/snowflake/sql/01_setup.sql
parallel_web_tools/integrations/snowflake/sql/02_create_udf.sql
parallel_web_tools/integrations/snowflake/sql/03_cleanup.sql
parallel_web_tools/integrations/spark/__init__.py
parallel_web_tools/integrations/spark/streaming.py
parallel_web_tools/integrations/spark/udf.py
parallel_web_tools/processors/__init__.py
parallel_web_tools/processors/bigquery.py
parallel_web_tools/processors/csv.py
parallel_web_tools/processors/duckdb.py
parallel_web_tools-0.0.11.dist-info/METADATA
parallel_web_tools-0.0.11.dist-info/WHEEL
parallel_web_tools-0.0.11.dist-info/entry_points.txt
parallel_web_tools-0.0.11.dist-info/RECORD
