Metadata-Version: 2.4
Name: parallel-web-tools
Version: 0.0.11
Summary: Parallel Tools: CLI and data enrichment utilities for the Parallel API
Project-URL: Homepage, https://github.com/parallel-web/parallel-web-tools
Project-URL: Documentation, https://docs.parallel.ai
Project-URL: Repository, https://github.com/parallel-web/parallel-web-tools
Project-URL: Issues, https://github.com/parallel-web/parallel-web-tools/issues
Author-email: Parallel <support@parallel.ai>
License-Expression: MIT
Keywords: ai,data-enrichment,data-pipeline,etl,llm,parallel,web-search
Classifier: Development Status :: 4 - Beta
Classifier: Intended Audience :: Developers
Classifier: License :: OSI Approved :: MIT License
Classifier: Operating System :: OS Independent
Classifier: Programming Language :: Python :: 3
Classifier: Programming Language :: Python :: 3.12
Classifier: Programming Language :: Python :: 3.13
Classifier: Topic :: Database
Classifier: Topic :: Scientific/Engineering :: Artificial Intelligence
Requires-Python: >=3.12
Requires-Dist: click>=8.1.0
Requires-Dist: httpx>=0.25.0
Requires-Dist: parallel-web>=0.4.0
Requires-Dist: python-dotenv>=1.0.0
Requires-Dist: rich>=13.0.0
Provides-Extra: all
Requires-Dist: duckdb>=1.0.0; extra == 'all'
Requires-Dist: nest-asyncio>=1.6.0; extra == 'all'
Requires-Dist: polars>=1.37.0; extra == 'all'
Requires-Dist: pyarrow>=18.0.0; extra == 'all'
Requires-Dist: pyyaml>=6.0.0; extra == 'all'
Requires-Dist: questionary>=2.0.0; extra == 'all'
Requires-Dist: snowflake-connector-python>=3.0.0; extra == 'all'
Requires-Dist: sqlalchemy-bigquery>=1.11.0; extra == 'all'
Requires-Dist: sqlalchemy>=2.0.0; extra == 'all'
Provides-Extra: bigquery
Requires-Dist: pyyaml>=6.0.0; extra == 'bigquery'
Requires-Dist: questionary>=2.0.0; extra == 'bigquery'
Requires-Dist: sqlalchemy-bigquery>=1.11.0; extra == 'bigquery'
Requires-Dist: sqlalchemy>=2.0.0; extra == 'bigquery'
Provides-Extra: bigquery-native
Provides-Extra: cli
Requires-Dist: pyyaml>=6.0.0; extra == 'cli'
Requires-Dist: questionary>=2.0.0; extra == 'cli'
Provides-Extra: dev
Requires-Dist: duckdb>=1.0.0; extra == 'dev'
Requires-Dist: nest-asyncio>=1.6.0; extra == 'dev'
Requires-Dist: pandas>=2.3.0; extra == 'dev'
Requires-Dist: polars>=1.37.0; extra == 'dev'
Requires-Dist: pre-commit>=4.0.0; extra == 'dev'
Requires-Dist: pyarrow>=18.0.0; extra == 'dev'
Requires-Dist: pyinstaller>=6.0.0; extra == 'dev'
Requires-Dist: pyrefly>=0.49.0; extra == 'dev'
Requires-Dist: pyspark>=3.4.0; extra == 'dev'
Requires-Dist: pytest-cov>=4.0.0; extra == 'dev'
Requires-Dist: pytest>=8.0.0; extra == 'dev'
Requires-Dist: pyyaml>=6.0.0; extra == 'dev'
Requires-Dist: questionary>=2.0.0; extra == 'dev'
Requires-Dist: ruff>=0.14.0; extra == 'dev'
Requires-Dist: snowflake-connector-python>=3.0.0; extra == 'dev'
Requires-Dist: sqlalchemy-bigquery>=1.11.0; extra == 'dev'
Requires-Dist: sqlalchemy>=2.0.0; extra == 'dev'
Provides-Extra: duckdb
Requires-Dist: duckdb>=1.0.0; extra == 'duckdb'
Requires-Dist: nest-asyncio>=1.6.0; extra == 'duckdb'
Requires-Dist: polars>=1.37.0; extra == 'duckdb'
Requires-Dist: pyarrow>=18.0.0; extra == 'duckdb'
Requires-Dist: pyyaml>=6.0.0; extra == 'duckdb'
Requires-Dist: questionary>=2.0.0; extra == 'duckdb'
Provides-Extra: pandas
Requires-Dist: pandas>=2.3.0; extra == 'pandas'
Provides-Extra: polars
Requires-Dist: polars>=1.37.0; extra == 'polars'
Requires-Dist: pyarrow>=18.0.0; extra == 'polars'
Provides-Extra: snowflake
Requires-Dist: snowflake-connector-python>=3.0.0; extra == 'snowflake'
Provides-Extra: spark
Requires-Dist: pandas>=2.3.0; extra == 'spark'
Requires-Dist: pyspark>=3.4.0; extra == 'spark'
